itemdb.py
itemdb-1.2.0.dist-info/LICENSE
itemdb-1.2.0.dist-info/METADATA
itemdb-1.2.0.dist-info/WHEEL
itemdb-1.2.0.dist-info/top_level.txt
itemdb-1.2.0.dist-info/zip-safe
itemdb-1.2.0.dist-info/RECORD
